plasmidkit/__init__.py
plasmidkit/api.py
plasmidkit/cli.py
plasmidkit/exporters.py
plasmidkit/annotate/__init__.py
plasmidkit/annotate/loader.py
plasmidkit/annotate/types.py
plasmidkit/annotate/detectors/__init__.py
plasmidkit/annotate/detectors/gc_length.py
plasmidkit/annotate/detectors/homopolymers.py
plasmidkit/annotate/detectors/marker.py
plasmidkit/annotate/detectors/orf_prodigal.py
plasmidkit/annotate/detectors/ori.py
plasmidkit/annotate/detectors/promoter.py
plasmidkit/annotate/detectors/repeats.py
plasmidkit/annotate/detectors/terminator.py
plasmidkit/annotate/detectors/utils.py
plasmidkit/cache/manager.py
plasmidkit/cache/registry.py
plasmidkit/data/__init__.py
plasmidkit/data/engineered_core_signatures.json
plasmidkit/scoring/calculator.py
plasmidkit/scoring/rules.py
plasmidkit-0.1.0.dist-info/METADATA
plasmidkit-0.1.0.dist-info/WHEEL
plasmidkit-0.1.0.dist-info/entry_points.txt
plasmidkit-0.1.0.dist-info/top_level.txt
plasmidkit-0.1.0.dist-info/RECORD
