Metadata-Version: 2.4
Name: plasmidkit
Version: 0.1.0
Summary: Fast Python library for plasmid annotation and makeability scoring
Author-email: PlasmidKit Maintainers <mcclain.thiel@gmail.com>
Requires-Python: >=3.10
Requires-Dist: biopython>=1.85
Requires-Dist: typer>=0.9
Requires-Dist: pyyaml>=6.0
Requires-Dist: pyahocorasick>=2.1.0
Requires-Dist: edlib>=1.3.9
Requires-Dist: pyrodigal>=3.6.3
Provides-Extra: fast
Requires-Dist: orjson>=3.9.0; extra == "fast"
Provides-Extra: full
Requires-Dist: moods-python>=1.9.4; extra == "full"
